{"id": "marieclaire-1938-03-11-a-p0013", "cdt": "2019-09-11 16:40:17", "r": [{"c": [590, 472, 814, 47], "p": [{"c": [590, 472, 814, 47], "l": [{"c": [590, 472, 814, 47], "t": [{"c": [590, 475, 130, 42], "tx": "LES"}, {"c": [797, 474, 200, 45], "tx": "YEUX"}, {"c": [1076, 472, 328, 44], "tx": "ROUGES"}]}]}], "pOf": "marieclaire-1938-03-11-a-i0132"}, {"c": [465, 545, 1001, 614], "p": [{"c": [465, 545, 1001, 614], "l": []}], "pOf": "marieclaire-1938-03-11-a-i0132"}, {"c": [586, 1204, 852, 867], "p": [{"c": [586, 1204, 852, 867], "l": [{"c": [586, 1204, 815, 39], "t": [{"c": [586, 1211, 30, 32], "tx": "SI"}, {"c": [664, 1209, 113, 33], "tx": "VOUS"}, {"c": [825, 1208, 101, 33], "tx": "AVEZ"}, {"c": [973, 1207, 63, 33], "tx": "LES"}, {"c": [1081, 1205, 104, 35], "tx": "YEUX"}, {"c": [1233, 1204, 168, 34], "tx": "ROUGES"}]}, {"c": [591, 1249, 815, 46], "t": [{"c": [591, 1254, 101, 41], "tx": "apr\u00e8s"}, {"c": [726, 1265, 66, 23], "tx": "une"}, {"c": [824, 1252, 148, 41], "tx": "journ\u00e9e"}, {"c": [1005, 1250, 121, 42], "tx": "pass\u00e9e"}, {"c": [1158, 1262, 42, 23], "tx": "en"}, {"c": [1231, 1250, 93, 41], "tx": "plein"}, {"c": [1353, 1249, 53, 35], "tx": "air"}]}, {"c": [590, 1294, 816, 47], "t": [{"c": [590, 1311, 47, 23], "tx": "ou"}, {"c": [672, 1299, 103, 42], "tx": "apr\u00e8s"}, {"c": [809, 1298, 101, 35], "tx": "avoir"}, {"c": [943, 1296, 162, 35], "tx": "travaill\u00e9"}, {"c": [1139, 1295, 20, 35], "tx": "\u00e0"}, {"c": [1191, 1296, 34, 34], "tx": "la"}, {"c": [1258, 1294, 148, 35], "tx": "lumi\u00e8re"}]}, {"c": [590, 1342, 814, 42], "t": [{"c": [590, 1344, 206, 40], "tx": "artificielle,"}, {"c": [824, 1343, 72, 34], "tx": "s'ils"}, {"c": [922, 1342, 201, 41], "tx": "rougissent"}, {"c": [1149, 1342, 142, 40], "tx": "lorsque"}, {"c": [1318, 1351, 86, 23], "tx": "vous"}]}, {"c": [591, 1385, 815, 44], "t": [{"c": [591, 1401, 89, 24], "tx": "vous"}, {"c": [709, 1396, 147, 28], "tx": "trouvez"}, {"c": [885, 1388, 87, 34], "tx": "dans"}, {"c": [1000, 1399, 67, 22], "tx": "une"}, {"c": [1095, 1387, 96, 42], "tx": "pi\u00e8ce"}, {"c": [1230, 1385, 176, 39], "tx": "enfum\u00e9e,"}]}, {"c": [593, 1430, 812, 44], "t": [{"c": [593, 1441, 128, 29], "tx": "mettez"}, {"c": [753, 1434, 86, 35], "tx": "dans"}, {"c": [870, 1445, 66, 23], "tx": "une"}, {"c": [964, 1432, 136, 35], "tx": "\u0153ill\u00e8re"}, {"c": [1131, 1443, 45, 24], "tx": "un"}, {"c": [1208, 1442, 66, 32], "tx": "peu"}, {"c": [1306, 1430, 99, 35], "tx": "d'eau"}]}, {"c": [593, 1476, 813, 42], "t": [{"c": [593, 1480, 93, 36], "tx": "sal\u00e9e"}, {"c": [718, 1479, 90, 35], "tx": "ti\u00e8de"}, {"c": [841, 1479, 82, 39], "tx": "(une"}, {"c": [954, 1477, 165, 36], "tx": "cuiller\u00e9e"}, {"c": [1149, 1476, 20, 37], "tx": "\u00e0"}, {"c": [1199, 1477, 135, 34], "tx": "bouche"}, {"c": [1363, 1476, 43, 34], "tx": "de"}]}, {"c": [593, 1521, 843, 46], "t": [{"c": [593, 1527, 49, 34], "tx": "sel"}, {"c": [675, 1526, 112, 34], "tx": "marin"}, {"c": [818, 1535, 89, 32], "tx": "pour"}, {"c": [938, 1535, 47, 23], "tx": "un"}, {"c": [1013, 1524, 80, 34], "tx": "litre"}, {"c": [1123, 1522, 116, 38], "tx": "d'eau)"}, {"c": [1271, 1529, 34, 28], "tx": "et"}, {"c": [1334, 1521, 72, 35], "tx": "bai--", "hy": true}]}, {"c": [593, 1569, 814, 44], "t": [{"c": [593, 1583, 86, 30], "tx": "gnez", "nf": "baignez"}, {"c": [709, 1571, 225, 40], "tx": "longuement"}, {"c": [964, 1570, 133, 34], "tx": "chacun"}, {"c": [1127, 1569, 43, 33], "tx": "de"}, {"c": [1209, 1579, 64, 23], "tx": "vos"}, {"c": [1313, 1578, 94, 31], "tx": "yeux"}]}, {"c": [594, 1613, 814, 42], "t": [{"c": [594, 1622, 154, 29], "tx": "ouverts."}, {"c": [807, 1615, 230, 40], "tx": "Maintenant,"}, {"c": [1095, 1613, 182, 35], "tx": "souhaitez"}, {"c": [1292, 1632, 12, 6], "tx": "-"}, {"c": [1318, 1624, 90, 24], "tx": "vous"}]}, {"c": [593, 1659, 842, 44], "t": [{"c": [593, 1663, 99, 34], "tx": "avoir"}, {"c": [715, 1662, 49, 34], "tx": "les"}, {"c": [784, 1672, 94, 31], "tx": "yeux"}, {"c": [898, 1660, 162, 34], "tx": "brillants"}, {"c": [1088, 1660, 14, 34], "tx": "?"}, {"c": [1125, 1659, 97, 34], "tx": "Dans"}, {"c": [1243, 1670, 67, 23], "tx": "une"}, {"c": [1331, 1659, 74, 34], "tx": "\u0153il--", "hy": true}]}, {"c": [593, 1705, 812, 42], "t": [{"c": [593, 1707, 70, 35], "tx": "l\u00e8re", "nf": "\u0153ill\u00e8re"}, {"c": [683, 1707, 101, 35], "tx": "d'eau"}, {"c": [804, 1707, 42, 35], "tx": "de"}, {"c": [866, 1718, 90, 29], "tx": "rose,"}, {"c": [976, 1706, 94, 34], "tx": "deux"}, {"c": [1090, 1717, 45, 23], "tx": "ou"}, {"c": [1156, 1705, 88, 34], "tx": "trois"}, {"c": [1263, 1711, 142, 35], "tx": "gouttes"}]}, {"c": [596, 1751, 813, 44], "t": [{"c": [596, 1754, 43, 35], "tx": "de"}, {"c": [670, 1753, 59, 42], "tx": "jus"}, {"c": [762, 1754, 167, 39], "tx": "d'orange"}, {"c": [961, 1752, 154, 34], "tx": "donnent"}, {"c": [1147, 1752, 61, 34], "tx": "des"}, {"c": [1241, 1751, 168, 35], "tx": "r\u00e9sultats"}]}, {"c": [595, 1797, 842, 37], "t": [{"c": [595, 1800, 242, 34], "tx": "merveilleux."}, {"c": [872, 1798, 37, 35], "tx": "Si"}, {"c": [940, 1809, 91, 24], "tx": "vous"}, {"c": [1063, 1797, 181, 35], "tx": "souhaitez"}, {"c": [1276, 1809, 46, 23], "tx": "un"}, {"c": [1355, 1808, 52, 22], "tx": "re--", "hy": true}]}, {"c": [596, 1842, 812, 45], "t": [{"c": [596, 1845, 101, 35], "tx": "m\u00e8de", "nf": "rem\u00e8de"}, {"c": [729, 1846, 77, 41], "tx": "plus"}, {"c": [839, 1844, 157, 40], "tx": "efficace,"}, {"c": [1031, 1844, 192, 34], "tx": "demandez"}, {"c": [1255, 1842, 21, 35], "tx": "\u00e0"}, {"c": [1306, 1849, 102, 28], "tx": "votre"}]}, {"c": [597, 1889, 841, 44], "t": [{"c": [597, 1891, 224, 42], "tx": "pharmacien"}, {"c": [850, 1890, 61, 34], "tx": "des"}, {"c": [940, 1890, 151, 41], "tx": "collyres"}, {"c": [1118, 1889, 59, 41], "tx": "qui"}, {"c": [1205, 1900, 90, 24], "tx": "vous"}, {"c": [1323, 1900, 85, 22], "tx": "vau--", "hy": true}]}, {"c": [597, 1936, 840, 42], "t": [{"c": [597, 1938, 105, 34], "tx": "dront", "nf": "vaudront"}, {"c": [722, 1937, 42, 35], "tx": "de"}, {"c": [784, 1937, 78, 34], "tx": "voir"}, {"c": [883, 1936, 212, 42], "tx": "dispara\u00eetre"}, {"c": [1116, 1937, 49, 34], "tx": "les"}, {"c": [1185, 1936, 120, 34], "tx": "veines"}, {"c": [1327, 1946, 80, 23], "tx": "rou--", "hy": true}]}, {"c": [597, 1981, 811, 43], "t": [{"c": [597, 1983, 140, 41], "tx": "ge\u00e2tres", "nf": "rou-ge\u00e2tres"}, {"c": [762, 1982, 59, 42], "tx": "qui"}, {"c": [849, 1983, 139, 34], "tx": "nuisent"}, {"c": [1015, 1981, 20, 35], "tx": "\u00e0"}, {"c": [1061, 1982, 33, 34], "tx": "la"}, {"c": [1121, 1981, 125, 35], "tx": "beaut\u00e9"}, {"c": [1274, 1981, 43, 34], "tx": "de"}, {"c": [1344, 1991, 64, 24], "tx": "vos"}]}, {"c": [596, 2026, 811, 45], "t": [{"c": [596, 2041, 103, 30], "tx": "yeux."}, {"c": [725, 2028, 85, 35], "tx": "Cela"}, {"c": [832, 2039, 91, 25], "tx": "vous"}, {"c": [944, 2028, 80, 42], "tx": "fera"}, {"c": [1049, 2027, 181, 42], "tx": "beaucoup"}, {"c": [1254, 2026, 43, 35], "tx": "de"}, {"c": [1321, 2027, 86, 34], "tx": "bien."}]}]}], "pOf": "marieclaire-1938-03-11-a-i0122"}, {"c": [1466, 375, 1176, 1758], "p": [{"c": [1466, 375, 1176, 1758], "l": []}], "pOf": "marieclaire-1938-03-11-a-i0133"}, {"c": [465, 2371, 1123, 1747], "p": [{"c": [465, 2371, 1123, 1747], "l": []}], "pOf": "marieclaire-1938-03-11-a-i0134"}, {"c": [1705, 2373, 937, 107], "p": [{"c": [1705, 2373, 937, 107], "l": [{"c": [1705, 2373, 937, 107], "t": [{"c": [1705, 2438, 41, 42], "tx": "N"}, {"c": [1746, 2438, 41, 42], "tx": "E"}, {"c": [1787, 2438, 64, 42], "tx": "Z"}, {"c": [1958, 2435, 213, 43], "tx": "TROP"}, {"c": [2281, 2421, 239, 56], "tx": "\u00c9PAIS"}, {"c": [2630, 2373, 12, 104], "tx": "I"}]}]}], "pOf": "marieclaire-1938-03-11-a-i0135"}, {"c": [1625, 2525, 1017, 1593], "p": [{"c": [1625, 2525, 1017, 1593], "l": []}], "pOf": "marieclaire-1938-03-11-a-i0135"}, {"c": [2888, 842, 875, 60], "p": [{"c": [2888, 842, 875, 60], "l": [{"c": [2888, 842, 875, 60], "t": [{"c": [2888, 856, 125, 41], "tx": "LES"}, {"c": [3077, 856, 196, 41], "tx": "YEUX"}, {"c": [3335, 842, 370, 59], "tx": "GONFLES"}, {"c": [3759, 895, 4, 7], "tx": ","}]}]}], "pOf": "marieclaire-1938-03-11-a-i0136"}, {"c": [2811, 942, 959, 1535], "p": [{"c": [2811, 942, 959, 1535], "l": []}], "pOf": "marieclaire-1938-03-11-a-i0136"}, {"c": [3770, 772, 1170, 1705], "p": [{"c": [3770, 772, 1170, 1705], "l": []}], "pOf": "marieclaire-1938-03-11-a-i0137"}, {"c": [2679, 2768, 1191, 1742], "p": [{"c": [2679, 2768, 1191, 1742], "l": []}], "pOf": "marieclaire-1938-03-11-a-i0138"}, {"c": [3983, 2806, 812, 60], "p": [{"c": [3983, 2806, 812, 60], "l": [{"c": [3983, 2806, 812, 60], "t": [{"c": [3983, 2826, 188, 39], "tx": "PAS"}, {"c": [4300, 2806, 495, 60], "tx": "COIFF\u00c9E"}]}]}], "pOf": "marieclaire-1938-03-11-a-i0139"}, {"c": [3913, 2895, 953, 741], "p": [{"c": [3913, 2895, 953, 741], "l": []}], "pOf": "marieclaire-1938-03-11-a-i0139"}, {"c": [3974, 3681, 845, 758], "p": [{"c": [3974, 3681, 845, 758], "l": [{"c": [3974, 3681, 811, 33], "t": [{"c": [3974, 3683, 30, 31], "tx": "SI"}, {"c": [4029, 3682, 111, 32], "tx": "VOUS"}, {"c": [4164, 3682, 142, 32], "tx": "N'AVEZ"}, {"c": [4327, 3682, 70, 31], "tx": "PAS"}, {"c": [4421, 3682, 39, 31], "tx": "LE"}, {"c": [4481, 3681, 124, 32], "tx": "TEMPS"}, {"c": [4628, 3681, 157, 32], "tx": "D'ALLER"}]}, {"c": [3975, 3724, 813, 40], "t": [{"c": [3975, 3726, 110, 33], "tx": "CHEZ"}, {"c": [4111, 3727, 39, 32], "tx": "LE"}, {"c": [4173, 3726, 211, 36], "tx": "COIFFEUR,"}, {"c": [4414, 3726, 125, 33], "tx": "sachez"}, {"c": [4558, 3737, 66, 27], "tx": "que"}, {"c": [4638, 3725, 33, 33], "tx": "la"}, {"c": [4685, 3724, 103, 34], "tx": "mode"}]}, {"c": [3975, 3763, 811, 41], "t": [{"c": [3975, 3771, 148, 33], "tx": "actuelle"}, {"c": [4145, 3770, 258, 34], "tx": "s'accommode"}, {"c": [4423, 3771, 120, 32], "tx": "mieux"}, {"c": [4565, 3763, 42, 41], "tx": "de"}, {"c": [4628, 3771, 158, 33], "tx": "cheveux"}]}, {"c": [3977, 3815, 810, 41], "t": [{"c": [3977, 3827, 46, 21], "tx": "un"}, {"c": [4050, 3827, 66, 28], "tx": "peu"}, {"c": [4144, 3826, 81, 30], "tx": "gras"}, {"c": [4254, 3827, 66, 28], "tx": "que"}, {"c": [4348, 3815, 41, 33], "tx": "de"}, {"c": [4417, 3816, 159, 33], "tx": "cheveux"}, {"c": [4605, 3821, 79, 35], "tx": "trop"}, {"c": [4712, 3826, 75, 22], "tx": "secs"}]}, {"c": [3976, 3860, 841, 34], "t": [{"c": [3976, 3868, 33, 26], "tx": "et"}, {"c": [4037, 3860, 205, 34], "tx": "\u00e9bouriff\u00e9s."}, {"c": [4272, 3861, 101, 33], "tx": "Vous"}, {"c": [4403, 3866, 186, 28], "tx": "remettrez"}, {"c": [4615, 3872, 64, 21], "tx": "vos"}, {"c": [4708, 3861, 79, 32], "tx": "che--", "hy": true}]}, {"c": [3977, 3904, 810, 41], "t": [{"c": [3977, 3917, 92, 22], "tx": "veux", "nf": "cheveux"}, {"c": [4091, 3917, 42, 22], "tx": "en"}, {"c": [4154, 3905, 65, 40], "tx": "plis"}, {"c": [4241, 3916, 85, 23], "tx": "avec"}, {"c": [4349, 3917, 66, 21], "tx": "une"}, {"c": [4438, 3905, 197, 33], "tx": "brillantine"}, {"c": [4657, 3904, 130, 41], "tx": "liquide"}]}, {"c": [3976, 3950, 810, 40], "t": [{"c": [3976, 3951, 43, 33], "tx": "de"}, {"c": [4047, 3950, 112, 33], "tx": "bonne"}, {"c": [4188, 3950, 139, 40], "tx": "qualit\u00e9."}, {"c": [4359, 3950, 38, 33], "tx": "Si"}, {"c": [4424, 3961, 89, 22], "tx": "vous"}, {"c": [4540, 3961, 90, 22], "tx": "vous"}, {"c": [4658, 3950, 128, 33], "tx": "coiffez"}]}, {"c": [3977, 3994, 809, 41], "t": [{"c": [3977, 4006, 84, 23], "tx": "avec"}, {"c": [4115, 3995, 61, 33], "tx": "des"}, {"c": [4229, 3995, 152, 39], "tx": "boucles,"}, {"c": [4435, 3995, 166, 33], "tx": "n'h\u00e9sitez"}, {"c": [4653, 4006, 63, 29], "tx": "pas"}, {"c": [4768, 3994, 18, 34], "tx": "\u00e0"}]}, {"c": [3980, 4040, 809, 41], "t": [{"c": [3980, 4040, 48, 33], "tx": "les"}, {"c": [4083, 4040, 131, 33], "tx": "refaire"}, {"c": [4267, 4052, 41, 21], "tx": "en"}, {"c": [4360, 4040, 151, 41], "tx": "gardant"}, {"c": [4563, 4053, 66, 21], "tx": "une"}, {"c": [4681, 4041, 108, 33], "tx": "heure"}]}, {"c": [3977, 4085, 810, 41], "t": [{"c": [3977, 4086, 167, 40], "tx": "quelques"}, {"c": [4188, 4085, 174, 40], "tx": "bigoudis."}, {"c": [4409, 4086, 77, 33], "tx": "Une"}, {"c": [4533, 4086, 71, 33], "tx": "fois"}, {"c": [4650, 4086, 137, 39], "tx": "coiff\u00e9e,"}]}, {"c": [3978, 4130, 838, 40], "t": [{"c": [3978, 4130, 28, 34], "tx": "si"}, {"c": [4031, 4142, 89, 21], "tx": "vous"}, {"c": [4144, 4131, 172, 33], "tx": "n'arrivez"}, {"c": [4339, 4142, 61, 28], "tx": "pas"}, {"c": [4424, 4130, 20, 33], "tx": "\u00e0"}, {"c": [4467, 4131, 163, 39], "tx": "dompter"}, {"c": [4654, 4131, 132, 39], "tx": "parfai--", "hy": true}]}, {"c": [3978, 4176, 810, 39], "t": [{"c": [3978, 4181, 130, 28], "tx": "tement", "nf": "parfaitement"}, {"c": [4141, 4176, 167, 39], "tx": "quelques"}, {"c": [4340, 4176, 160, 33], "tx": "cheveux"}, {"c": [4535, 4176, 92, 39], "tx": "fous,"}, {"c": [4662, 4182, 126, 27], "tx": "mettez"}]}, {"c": [3980, 4219, 839, 41], "t": [{"c": [3980, 4219, 85, 34], "tx": "dans"}, {"c": [4085, 4220, 31, 33], "tx": "le"}, {"c": [4135, 4231, 109, 22], "tx": "creux"}, {"c": [4264, 4219, 42, 34], "tx": "de"}, {"c": [4325, 4221, 33, 32], "tx": "la"}, {"c": [4378, 4220, 92, 33], "tx": "main"}, {"c": [4491, 4232, 44, 21], "tx": "un"}, {"c": [4555, 4232, 65, 28], "tx": "peu"}, {"c": [4641, 4220, 42, 34], "tx": "de"}, {"c": [4702, 4221, 87, 33], "tx": "tein--", "hy": true}]}, {"c": [3980, 4264, 839, 41], "t": [{"c": [3980, 4270, 78, 28], "tx": "ture", "nf": "teinture"}, {"c": [4086, 4265, 42, 32], "tx": "de"}, {"c": [4156, 4264, 141, 40], "tx": "benjoin"}, {"c": [4325, 4271, 33, 27], "tx": "et"}, {"c": [4384, 4276, 122, 29], "tx": "passez"}, {"c": [4534, 4277, 60, 21], "tx": "sur"}, {"c": [4621, 4276, 63, 22], "tx": "vos"}, {"c": [4711, 4266, 78, 33], "tx": "che--", "hy": true}]}, {"c": [3980, 4309, 810, 41], "t": [{"c": [3980, 4320, 94, 23], "tx": "veux", "nf": "cheveux"}, {"c": [4116, 4320, 5, 22], "tx": ":"}, {"c": [4156, 4310, 40, 32], "tx": "ils"}, {"c": [4228, 4320, 36, 22], "tx": "se"}, {"c": [4296, 4316, 208, 27], "tx": "trouveront"}, {"c": [4536, 4309, 119, 41], "tx": "laqu\u00e9s"}, {"c": [4686, 4316, 32, 27], "tx": "et"}, {"c": [4749, 4322, 41, 21], "tx": "ne"}]}, {"c": [3980, 4353, 808, 41], "t": [{"c": [3980, 4354, 236, 33], "tx": "s'envoleront"}, {"c": [4260, 4355, 87, 39], "tx": "plus."}, {"c": [4393, 4353, 83, 34], "tx": "Cela"}, {"c": [4521, 4366, 90, 23], "tx": "vous"}, {"c": [4654, 4354, 134, 34], "tx": "vaudra"}]}, {"c": [3983, 4399, 806, 40], "t": [{"c": [3983, 4399, 42, 33], "tx": "de"}, {"c": [4055, 4404, 114, 27], "tx": "rester"}, {"c": [4201, 4399, 209, 40], "tx": "impeccable"}, {"c": [4444, 4406, 95, 27], "tx": "toute"}, {"c": [4569, 4412, 67, 21], "tx": "une"}, {"c": [4667, 4400, 122, 34], "tx": "soir\u00e9e."}]}]}], "pOf": "marieclaire-1938-03-11-a-i0122"}, {"c": [5252, 423, 671, 49], "p": [{"c": [5252, 423, 671, 49], "l": [{"c": [5252, 423, 671, 49], "t": [{"c": [5252, 423, 401, 45], "tx": "MAUVAISE"}, {"c": [5736, 428, 187, 44], "tx": "MINE"}]}]}], "pOf": "marieclaire-1938-03-11-a-i0140"}, {"c": [5030, 502, 1048, 620], "p": [{"c": [5030, 502, 1048, 620], "l": []}], "pOf": "marieclaire-1938-03-11-a-i0140"}, {"c": [5171, 1167, 850, 634], "p": [{"c": [5171, 1167, 850, 634], "l": [{"c": [5174, 1167, 816, 44], "t": [{"c": [5174, 1168, 35, 35], "tx": "SI"}, {"c": [5238, 1167, 128, 36], "tx": "VOUS"}, {"c": [5392, 1168, 113, 36], "tx": "AVEZ"}, {"c": [5536, 1168, 231, 37], "tx": "MAUVAISE"}, {"c": [5792, 1170, 128, 41], "tx": "MINE,"}, {"c": [5952, 1184, 38, 20], "tx": "ne"}]}, {"c": [5176, 1216, 814, 40], "t": [{"c": [5176, 1226, 120, 27], "tx": "croyez"}, {"c": [5326, 1226, 58, 28], "tx": "pas"}, {"c": [5414, 1216, 96, 38], "tx": "qu'en"}, {"c": [5538, 1222, 140, 27], "tx": "mettant"}, {"c": [5708, 1217, 211, 39], "tx": "simplement"}, {"c": [5945, 1218, 45, 31], "tx": "dit"}]}, {"c": [5178, 1268, 843, 34], "t": [{"c": [5178, 1271, 105, 27], "tx": "ronge"}, {"c": [5318, 1272, 55, 21], "tx": "sur"}, {"c": [5410, 1272, 58, 21], "tx": "vos"}, {"c": [5502, 1268, 200, 32], "tx": "pommettes"}, {"c": [5736, 1272, 83, 23], "tx": "vous"}, {"c": [5853, 1272, 138, 30], "tx": "repren--", "hy": true}]}, {"c": [5176, 1307, 814, 38], "t": [{"c": [5176, 1307, 79, 31], "tx": "drez", "nf": "reprendrez"}, {"c": [5300, 1317, 82, 28], "tx": "pour"}, {"c": [5428, 1317, 41, 22], "tx": "un"}, {"c": [5516, 1307, 66, 32], "tx": "soir"}, {"c": [5625, 1318, 46, 22], "tx": "un"}, {"c": [5711, 1307, 85, 33], "tx": "teint"}, {"c": [5838, 1308, 152, 33], "tx": "radieux."}]}, {"c": [5180, 1351, 811, 39], "t": [{"c": [5180, 1351, 184, 39], "tx": "Employez"}, {"c": [5409, 1363, 131, 22], "tx": "comme"}, {"c": [5590, 1352, 83, 33], "tx": "fond"}, {"c": [5715, 1353, 41, 33], "tx": "de"}, {"c": [5800, 1353, 83, 33], "tx": "teint"}, {"c": [5927, 1364, 64, 23], "tx": "une"}]}, {"c": [5176, 1397, 814, 41], "t": [{"c": [5176, 1397, 113, 32], "tx": "cr\u00e8me"}, {"c": [5320, 1408, 94, 21], "tx": "assez"}, {"c": [5448, 1398, 124, 38], "tx": "liquide"}, {"c": [5602, 1403, 41, 34], "tx": "et,"}, {"c": [5674, 1406, 105, 26], "tx": "avant"}, {"c": [5806, 1399, 184, 39], "tx": "d'essuyer."}]}, {"c": [5177, 1443, 811, 40], "t": [{"c": [5177, 1448, 120, 27], "tx": "mettez"}, {"c": [5334, 1453, 62, 22], "tx": "une"}, {"c": [5431, 1443, 101, 39], "tx": "petite"}, {"c": [5565, 1443, 122, 33], "tx": "touche"}, {"c": [5719, 1444, 40, 33], "tx": "de"}, {"c": [5794, 1454, 105, 29], "tx": "rouge"}, {"c": [5932, 1456, 56, 21], "tx": "sur"}]}, {"c": [5177, 1487, 814, 42], "t": [{"c": [5177, 1495, 95, 25], "tx": "votre"}, {"c": [5311, 1487, 103, 40], "tx": "front,"}, {"c": [5450, 1499, 58, 22], "tx": "sur"}, {"c": [5545, 1494, 97, 28], "tx": "votre"}, {"c": [5673, 1499, 66, 23], "tx": "cou"}, {"c": [5771, 1495, 32, 27], "tx": "et"}, {"c": [5836, 1489, 79, 40], "tx": "pr\u00e8s"}, {"c": [5947, 1490, 44, 34], "tx": "de"}]}, {"c": [5176, 1533, 841, 37], "t": [{"c": [5176, 1533, 151, 37], "tx": "l'oreille,"}, {"c": [5360, 1533, 106, 33], "tx": "m\u00ealez"}, {"c": [5499, 1534, 211, 34], "tx": "i.ntimement"}, {"c": [5741, 1546, 81, 22], "tx": "avec"}, {"c": [5854, 1538, 31, 30], "tx": "la"}, {"c": [5917, 1536, 70, 32], "tx": "cr\u00e8--", "hy": true}]}, {"c": [5177, 1578, 812, 36], "t": [{"c": [5177, 1589, 51, 21], "tx": "me", "nf": "cr\u00e8me"}, {"c": [5259, 1579, 40, 32], "tx": "de"}, {"c": [5330, 1578, 150, 34], "tx": "mani\u00e8re"}, {"c": [5511, 1580, 18, 32], "tx": "\u00e0"}, {"c": [5560, 1580, 128, 34], "tx": "donner"}, {"c": [5720, 1580, 161, 34], "tx": "l'illusion"}, {"c": [5911, 1580, 78, 33], "tx": "d'un"}]}, {"c": [5176, 1623, 813, 40], "t": [{"c": [5176, 1623, 81, 33], "tx": "teint"}, {"c": [5293, 1624, 120, 34], "tx": "anim\u00e9."}, {"c": [5451, 1625, 161, 38], "tx": "Essuyez,"}, {"c": [5647, 1631, 31, 28], "tx": "et"}, {"c": [5713, 1626, 145, 34], "tx": "achevez"}, {"c": [5893, 1632, 96, 27], "tx": "votre"}]}, {"c": [5171, 1670, 847, 42], "t": [{"c": [5171, 1670, 211, 38], "tx": "maquillage"}, {"c": [5419, 1681, 130, 22], "tx": "comme"}, {"c": [5586, 1670, 204, 34], "tx": "d'habitude."}, {"c": [5829, 1672, 46, 33], "tx": "Ce"}, {"c": [5910, 1678, 78, 34], "tx": "p-ro--", "hy": true}]}, {"c": [5174, 1714, 815, 41], "t": [{"c": [5174, 1715, 80, 32], "tx": "cede", "nf": "p-ro-cede"}, {"c": [5297, 1716, 69, 31], "tx": "tr\u00e8s"}, {"c": [5405, 1714, 120, 41], "tx": "simple"}, {"c": [5565, 1727, 85, 21], "tx": "vous"}, {"c": [5689, 1717, 127, 32], "tx": "vaudra"}, {"c": [5857, 1717, 132, 33], "tx": "d'avoir"}]}, {"c": [5176, 1760, 810, 41], "t": [{"c": [5176, 1771, 61, 22], "tx": "une"}, {"c": [5290, 1760, 85, 32], "tx": "mine"}, {"c": [5425, 1761, 135, 38], "tx": "fra\u00eeche"}, {"c": [5610, 1766, 31, 28], "tx": "et"}, {"c": [5690, 1762, 296, 39], "tx": "rc'.\u00ee/'lclldissalltc."}]}]}], "pOf": "marieclaire-1938-03-11-a-i0122"}, {"c": [6121, 391, 1117, 1419], "p": [{"c": [6121, 391, 1117, 1419], "l": []}], "pOf": "marieclaire-1938-03-11-a-i0141"}, {"c": [4940, 1942, 1811, 2663], "p": [{"c": [4940, 1942, 1811, 2663], "l": []}], "pOf": "marieclaire-1938-03-11-a-i0142"}, {"c": [6370, 3844, 707, 454], "p": [{"c": [6370, 3844, 707, 454], "l": [{"c": [6370, 3844, 706, 49], "t": [{"c": [6370, 3844, 39, 40], "tx": "f"}, {"c": [6437, 3879, 41, 10], "tx": "..."}, {"c": [6488, 3852, 49, 36], "tx": "ET"}, {"c": [6593, 3850, 310, 43], "tx": "MAINTENANT,"}, {"c": [6957, 3849, 119, 37], "tx": "POUR"}]}, {"c": [6436, 3895, 640, 38], "t": [{"c": [6436, 3896, 160, 37], "tx": "METTRE"}, {"c": [6625, 3896, 64, 36], "tx": "UN"}, {"c": [6721, 3895, 137, 37], "tx": "POINT"}, {"c": [6887, 3895, 122, 36], "tx": "FINAL"}, {"c": [7043, 3895, 33, 34], "tx": "A"}]}, {"c": [6436, 3931, 641, 51], "t": [{"c": [6436, 3942, 167, 36], "tx": "VOTRE"}, {"c": [6637, 3931, 205, 51], "tx": "BEAUT\u00c9,"}, {"c": [6888, 3943, 111, 32], "tx": "battez"}, {"c": [7033, 3952, 44, 23], "tx": "un"}]}, {"c": [6438, 3986, 637, 41], "t": [{"c": [6438, 3989, 97, 34], "tx": "blanc"}, {"c": [6559, 3989, 107, 34], "tx": "d'oeuf"}, {"c": [6692, 3999, 41, 23], "tx": "en"}, {"c": [6755, 3987, 107, 40], "tx": "neige."}, {"c": [6885, 3986, 190, 41], "tx": "Appliquez"}]}, {"c": [6440, 4032, 637, 39], "t": [{"c": [6440, 4035, 31, 33], "tx": "la"}, {"c": [6494, 4045, 136, 22], "tx": "mousse"}, {"c": [6655, 4044, 57, 23], "tx": "sur"}, {"c": [6737, 4038, 98, 29], "tx": "votre"}, {"c": [6856, 4032, 116, 39], "tx": "visage"}, {"c": [6994, 4042, 83, 22], "tx": "avec"}]}, {"c": [6439, 4074, 638, 39], "t": [{"c": [6439, 4090, 45, 23], "tx": "un"}, {"c": [6511, 4079, 161, 33], "tx": "blaireau."}, {"c": [6704, 4078, 136, 33], "tx": "Laissez"}, {"c": [6871, 4076, 116, 35], "tx": "s\u00e9cher"}, {"c": [7018, 4074, 59, 35], "tx": "dix"}]}, {"c": [6437, 4120, 638, 37], "t": [{"c": [6437, 4123, 156, 34], "tx": "minutes."}, {"c": [6633, 4122, 124, 34], "tx": "Rincez"}, {"c": [6796, 4122, 20, 33], "tx": "\u00e0"}, {"c": [6855, 4121, 85, 33], "tx": "l'eau"}, {"c": [6977, 4120, 98, 34], "tx": "ti\u00e8de."}]}, {"c": [6436, 4172, 638, 42], "t": [{"c": [6436, 4172, 137, 37], "tx": "VOUS"}, {"c": [6602, 4173, 164, 35], "tx": "AUREZ"}, {"c": [6801, 4172, 185, 42], "tx": "ALORS,"}, {"c": [7014, 4172, 60, 35], "tx": "CE"}]}, {"c": [6435, 4216, 639, 37], "t": [{"c": [6435, 4216, 137, 37], "tx": "SOIR,"}, {"c": [6615, 4217, 47, 35], "tx": "LE"}, {"c": [6714, 4217, 252, 36], "tx": "MAXIMUM"}, {"c": [7014, 4217, 60, 35], "tx": "DE"}]}, {"c": [6436, 4252, 636, 46], "t": [{"c": [6436, 4261, 286, 37], "tx": "FRAICHEUR"}, {"c": [6768, 4262, 50, 35], "tx": "ET"}, {"c": [6855, 4252, 217, 46], "tx": "D'\u00c9CLAT."}]}]}], "pOf": "marieclaire-1938-03-11-a-i0142"}], "iiif": "https://gallica.bnf.fr/iiif/ark:/12148/bpt6k4701034k/f13/full/full/0/manifest.json", "cc": false}